README.md
setup.py
quick_resto_API/__init__.py
quick_resto_API/quick_resto_api.py
quick_resto_API/quick_resto_interface.py
quick_resto_API.egg-info/PKG-INFO
quick_resto_API.egg-info/SOURCES.txt
quick_resto_API.egg-info/dependency_links.txt
quick_resto_API.egg-info/top_level.txt
quick_resto_API/class_generator/class_generator.py
quick_resto_API/operations_with_objects/operations_with_objects.py
quick_resto_API/operations_with_objects/system_object.py
quick_resto_API/operations_with_objects/list_request/filter.py
quick_resto_API/operations_with_objects/list_request/list_request.py
quick_resto_API/operations_with_objects/modules/account_type_operations.py
quick_resto_API/operations_with_objects/modules/alcohol_dictionary_operations.py
quick_resto_API/operations_with_objects/modules/alcohol_report_operations.py
quick_resto_API/operations_with_objects/modules/bonus_program_operations.py
quick_resto_API/operations_with_objects/modules/business_operations.py
quick_resto_API/operations_with_objects/modules/cancellation_operations.py
quick_resto_API/operations_with_objects/modules/company_info_operations.py
quick_resto_API/operations_with_objects/modules/cooking_invoice_operations.py
quick_resto_API/operations_with_objects/modules/cooking_place_operations.py
quick_resto_API/operations_with_objects/modules/crm_customer_operations.py
quick_resto_API/operations_with_objects/modules/decomposition_invoice_operations.py
quick_resto_API/operations_with_objects/modules/discard_invoice_operations.py
quick_resto_API/operations_with_objects/modules/dish_operations.py
quick_resto_API/operations_with_objects/modules/employee_operations.py
quick_resto_API/operations_with_objects/modules/encashment_operations.py
quick_resto_API/operations_with_objects/modules/exchange_invoice_operations.py
quick_resto_API/operations_with_objects/modules/fixed_discount_operations.py
quick_resto_API/operations_with_objects/modules/hall_operations.py
quick_resto_API/operations_with_objects/modules/incoming_invoice_operations.py
quick_resto_API/operations_with_objects/modules/inventory_document_operations.py
