Metadata-Version: 2.1
Name: quick-resto-API
Version: 1.2.5
Summary: Quick Resto API
Author: sergeyrukin
Author-email: sergey.rukin1425@gmail.com
